[{"name":"Atlantean (World) (Aftermarket) (Unl).zip","url":"https://myrient.erista.me/files/No-Intro/NEC%20-%20PC%20Engine%20-%20TurboGrafx-16%20%28Private%29/Atlantean%20%28World%29%20%28Aftermarket%29%20%28Unl%29.zip","size":"91.9 KiB","path":["No-Intro","NEC - PC Engine - TurboGrafx-16 (Private)"]},{"name":"Atlantean (World) (Itch.io) (Aftermarket) (Unl).zip","url":"https://myrient.erista.me/files/No-Intro/NEC%20-%20PC%20Engine%20-%20TurboGrafx-16%20%28Private%29/Atlantean%20%28World%29%20%28Itch.io%29%20%28Aftermarket%29%20%28Unl%29.zip","size":"91.9 KiB","path":["No-Intro","NEC - PC Engine - TurboGrafx-16 (Private)"]},{"name":"Billy's Bad Day (World) (Digital) (Aftermarket) (Unl).zip","url":"https://myrient.erista.me/files/No-Intro/NEC%20-%20PC%20Engine%20-%20TurboGrafx-16%20%28Private%29/Billy%27s%20Bad%20Day%20%28World%29%20%28Digital%29%20%28Aftermarket%29%20%28Unl%29.zip","size":"359.6 KiB","path":["No-Intro","NEC - PC Engine - TurboGrafx-16 (Private)"]}]