[{"name":"Heikinten Bar Graph (1984-12)(Tochigi, Masaru)(JP)[Micom BASIC].zip","url":"https://myrient.erista.me/files/TOSEC/Matsushita/JR-100/Educational/Heikinten%20Bar%20Graph%20%281984-12%29%28Tochigi%2C%20Masaru%29%28JP%29%5BMicom%20BASIC%5D.zip","size":"164.3 KiB","path":["TOSEC","Matsushita","JR-100","Educational"]},{"name":"Ascend (2022-04-02)(Inufuto)(JP).zip","url":"https://myrient.erista.me/files/TOSEC/Matsushita/JR-100/Games/%5BPRG%5D/Ascend%20%282022-04-02%29%28Inufuto%29%28JP%29.zip","size":"5.5 KiB","path":["TOSEC","Matsushita","JR-100","Games","[PRG]"]},{"name":"Mazy (2020)(Inufuto)(JP).zip","url":"https://myrient.erista.me/files/TOSEC/Matsushita/JR-100/Games/%5BPRG%5D/Mazy%20%282020%29%28Inufuto%29%28JP%29.zip","size":"4.8 KiB","path":["TOSEC","Matsushita","JR-100","Games","[PRG]"]},{"name":"Ruptus (2020-12-06)(Inufuto)(JP).zip","url":"https://myrient.erista.me/files/TOSEC/Matsushita/JR-100/Games/%5BPRG%5D/Ruptus%20%282020-12-06%29%28Inufuto%29%28JP%29.zip","size":"8.2 KiB","path":["TOSEC","Matsushita","JR-100","Games","[PRG]"]},{"name":"Ascend (2022-04-02)(Inufuto)(JP).zip","url":"https://myrient.erista.me/files/TOSEC/Matsushita/JR-100/Games/%5BWAV%5D/Ascend%20%282022-04-02%29%28Inufuto%29%28JP%29.zip","size":"40.3 KiB","path":["TOSEC","Matsushita","JR-100","Games","[WAV]"]},{"name":"Mazy (2020)(Inufuto)(JP).zip","url":"https://myrient.erista.me/files/TOSEC/Matsushita/JR-100/Games/%5BWAV%5D/Mazy%20%282020%29%28Inufuto%29%28JP%29.zip","size":"124.6 KiB","path":["TOSEC","Matsushita","JR-100","Games","[WAV]"]},{"name":"Ruptus (2020-12-06)(Inufuto)(JP).zip","url":"https://myrient.erista.me/files/TOSEC/Matsushita/JR-100/Games/%5BWAV%5D/Ruptus%20%282020-12-06%29%28Inufuto%29%28JP%29.zip","size":"59.6 KiB","path":["TOSEC","Matsushita","JR-100","Games","[WAV]"]}]