[{"name":"playcenter_celeron_9.3_tournament.chd","url":"https://myrient.erista.me/files/MAME/CHDs%20%28merged%29/plycntrchtr/playcenter_celeron_9.3_tournament.chd","size":"595.6 MiB","path":["MAME","CHDs (merged)","plycntrchtr"]},{"name":"playcenter_epox_9.3_tournament.chd","url":"https://myrient.erista.me/files/MAME/CHDs%20%28merged%29/plycntrchtr/playcenter_epox_9.3_tournament.chd","size":"625.2 MiB","path":["MAME","CHDs (merged)","plycntrchtr"]},{"name":"playcenter_k6_9.3_tournament.chd","url":"https://myrient.erista.me/files/MAME/CHDs%20%28merged%29/plycntrchtr/playcenter_k6_9.3_tournament.chd","size":"628.1 MiB","path":["MAME","CHDs (merged)","plycntrchtr"]}]