[{"name":"arion.zip","url":"https://myrient.erista.me/files/MAME/Software%20List%20ROMs%20%28split%29/mz2500_flop/arion.zip","size":"496.1 KiB","path":["MAME","Software List ROMs (split)","mz2500_flop"]},{"name":"backtof.zip","url":"https://myrient.erista.me/files/MAME/Software%20List%20ROMs%20%28split%29/mz2500_flop/backtof.zip","size":"420.0 KiB","path":["MAME","Software List ROMs (split)","mz2500_flop"]},{"name":"balonfgt.zip","url":"https://myrient.erista.me/files/MAME/Software%20List%20ROMs%20%28split%29/mz2500_flop/balonfgt.zip","size":"21.5 KiB","path":["MAME","Software List ROMs (split)","mz2500_flop"]},{"name":"basicv1.zip","url":"https://myrient.erista.me/files/MAME/Software%20List%20ROMs%20%28split%29/mz2500_flop/basicv1.zip","size":"237.7 KiB","path":["MAME","Software List ROMs (split)","mz2500_flop"]},{"name":"basicv2.zip","url":"https://myrient.erista.me/files/MAME/Software%20List%20ROMs%20%28split%29/mz2500_flop/basicv2.zip","size":"263.1 KiB","path":["MAME","Software List ROMs (split)","mz2500_flop"]},{"name":"blckonyx.zip","url":"https://myrient.erista.me/files/MAME/Software%20List%20ROMs%20%28split%29/mz2500_flop/blckonyx.zip","size":"258.2 KiB","path":["MAME","Software List ROMs (split)","mz2500_flop"]},{"name":"druaga.zip","url":"https://myrient.erista.me/files/MAME/Software%20List%20ROMs%20%28split%29/mz2500_flop/druaga.zip","size":"76.4 KiB","path":["MAME","Software List ROMs (split)","mz2500_flop"]},{"name":"dustbx01.zip","url":"https://myrient.erista.me/files/MAME/Software%20List%20ROMs%20%28split%29/mz2500_flop/dustbx01.zip","size":"264.3 KiB","path":["MAME","Software List ROMs (split)","mz2500_flop"]},{"name":"dustbx02.zip","url":"https://myrient.erista.me/files/MAME/Software%20List%20ROMs%20%28split%29/mz2500_flop/dustbx02.zip","size":"286.2 KiB","path":["MAME","Software List ROMs (split)","mz2500_flop"]},{"name":"dustbx03.zip","url":"https://myrient.erista.me/files/MAME/Software%20List%20ROMs%20%28split%29/mz2500_flop/dustbx03.zip","size":"296.9 KiB","path":["MAME","Software List ROMs (split)","mz2500_flop"]},{"name":"dustbx04.zip","url":"https://myrient.erista.me/files/MAME/Software%20List%20ROMs%20%28split%29/mz2500_flop/dustbx04.zip","size":"302.6 KiB","path":["MAME","Software List ROMs (split)","mz2500_flop"]},{"name":"dustbx05.zip","url":"https://myrient.erista.me/files/MAME/Software%20List%20ROMs%20%28split%29/mz2500_flop/dustbx05.zip","size":"307.4 KiB","path":["MAME","Software List ROMs (split)","mz2500_flop"]},{"name":"dustbx06.zip","url":"https://myrient.erista.me/files/MAME/Software%20List%20ROMs%20%28split%29/mz2500_flop/dustbx06.zip","size":"317.6 KiB","path":["MAME","Software List ROMs (split)","mz2500_flop"]},{"name":"dustbx07.zip","url":"https://myrient.erista.me/files/MAME/Software%20List%20ROMs%20%28split%29/mz2500_flop/dustbx07.zip","size":"278.7 KiB","path":["MAME","Software List ROMs (split)","mz2500_flop"]},{"name":"dustbx08.zip","url":"https://myrient.erista.me/files/MAME/Software%20List%20ROMs%20%28split%29/mz2500_flop/dustbx08.zip","size":"291.9 KiB","path":["MAME","Software List ROMs (split)","mz2500_flop"]},{"name":"dustbx09.zip","url":"https://myrient.erista.me/files/MAME/Software%20List%20ROMs%20%28split%29/mz2500_flop/dustbx09.zip","size":"292.4 KiB","path":["MAME","Software List ROMs (split)","mz2500_flop"]},{"name":"dustbx10.zip","url":"https://myrient.erista.me/files/MAME/Software%20List%20ROMs%20%28split%29/mz2500_flop/dustbx10.zip","size":"275.9 KiB","path":["MAME","Software List ROMs (split)","mz2500_flop"]},{"name":"dustbx11.zip","url":"https://myrient.erista.me/files/MAME/Software%20List%20ROMs%20%28split%29/mz2500_flop/dustbx11.zip","size":"342.2 KiB","path":["MAME","Software List ROMs (split)","mz2500_flop"]},{"name":"dustbx12.zip","url":"https://myrient.erista.me/files/MAME/Software%20List%20ROMs%20%28split%29/mz2500_flop/dustbx12.zip","size":"341.5 KiB","path":["MAME","Software List ROMs (split)","mz2500_flop"]},{"name":"dustbx13.zip","url":"https://myrient.erista.me/files/MAME/Software%20List%20ROMs%20%28split%29/mz2500_flop/dustbx13.zip","size":"325.6 KiB","path":["MAME","Software List ROMs (split)","mz2500_flop"]},{"name":"dustbx14.zip","url":"https://myrient.erista.me/files/MAME/Software%20List%20ROMs%20%28split%29/mz2500_flop/dustbx14.zip","size":"380.4 KiB","path":["MAME","Software List ROMs (split)","mz2500_flop"]},{"name":"dustbx15.zip","url":"https://myrient.erista.me/files/MAME/Software%20List%20ROMs%20%28split%29/mz2500_flop/dustbx15.zip","size":"309.1 KiB","path":["MAME","Software List ROMs (split)","mz2500_flop"]},{"name":"dustbx16.zip","url":"https://myrient.erista.me/files/MAME/Software%20List%20ROMs%20%28split%29/mz2500_flop/dustbx16.zip","size":"293.7 KiB","path":["MAME","Software List ROMs (split)","mz2500_flop"]},{"name":"dustbx91.zip","url":"https://myrient.erista.me/files/MAME/Software%20List%20ROMs%20%28split%29/mz2500_flop/dustbx91.zip","size":"358.4 KiB","path":["MAME","Software List ROMs (split)","mz2500_flop"]},{"name":"eiyuden.zip","url":"https://myrient.erista.me/files/MAME/Software%20List%20ROMs%20%28split%29/mz2500_flop/eiyuden.zip","size":"592.9 KiB","path":["MAME","Software List ROMs (split)","mz2500_flop"]},{"name":"excitbik.zip","url":"https://myrient.erista.me/files/MAME/Software%20List%20ROMs%20%28split%29/mz2500_flop/excitbik.zip","size":"25.8 KiB","path":["MAME","Software List ROMs (split)","mz2500_flop"]},{"name":"f2gp.zip","url":"https://myrient.erista.me/files/MAME/Software%20List%20ROMs%20%28split%29/mz2500_flop/f2gp.zip","size":"1.1 MiB","path":["MAME","Software List ROMs (split)","mz2500_flop"]},{"name":"fenix.zip","url":"https://myrient.erista.me/files/MAME/Software%20List%20ROMs%20%28split%29/mz2500_flop/fenix.zip","size":"160.7 KiB","path":["MAME","Software List ROMs (split)","mz2500_flop"]},{"name":"firecrys.zip","url":"https://myrient.erista.me/files/MAME/Software%20List%20ROMs%20%28split%29/mz2500_flop/firecrys.zip","size":"277.5 KiB","path":["MAME","Software List ROMs (split)","mz2500_flop"]},{"name":"galaga.zip","url":"https://myrient.erista.me/files/MAME/Software%20List%20ROMs%20%28split%29/mz2500_flop/galaga.zip","size":"92.1 KiB","path":["MAME","Software List ROMs (split)","mz2500_flop"]},{"name":"gomokuna.zip","url":"https://myrient.erista.me/files/MAME/Software%20List%20ROMs%20%28split%29/mz2500_flop/gomokuna.zip","size":"127.4 KiB","path":["MAME","Software List ROMs (split)","mz2500_flop"]},{"name":"hashires.zip","url":"https://myrient.erista.me/files/MAME/Software%20List%20ROMs%20%28split%29/mz2500_flop/hashires.zip","size":"109.1 KiB","path":["MAME","Software List ROMs (split)","mz2500_flop"]},{"name":"hfox.zip","url":"https://myrient.erista.me/files/MAME/Software%20List%20ROMs%20%28split%29/mz2500_flop/hfox.zip","size":"526.8 KiB","path":["MAME","Software List ROMs (split)","mz2500_flop"]},{"name":"hoveratk.zip","url":"https://myrient.erista.me/files/MAME/Software%20List%20ROMs%20%28split%29/mz2500_flop/hoveratk.zip","size":"37.0 KiB","path":["MAME","Software List ROMs (split)","mz2500_flop"]},{"name":"kaleidos.zip","url":"https://myrient.erista.me/files/MAME/Software%20List%20ROMs%20%28split%29/mz2500_flop/kaleidos.zip","size":"427.2 KiB","path":["MAME","Software List ROMs (split)","mz2500_flop"]},{"name":"kingflap.zip","url":"https://myrient.erista.me/files/MAME/Software%20List%20ROMs%20%28split%29/mz2500_flop/kingflap.zip","size":"91.0 KiB","path":["MAME","Software List ROMs (split)","mz2500_flop"]},{"name":"kitahei.zip","url":"https://myrient.erista.me/files/MAME/Software%20List%20ROMs%20%28split%29/mz2500_flop/kitahei.zip","size":"65.3 KiB","path":["MAME","Software List ROMs (split)","mz2500_flop"]},{"name":"laydock.zip","url":"https://myrient.erista.me/files/MAME/Software%20List%20ROMs%20%28split%29/mz2500_flop/laydock.zip","size":"192.8 KiB","path":["MAME","Software List ROMs (split)","mz2500_flop"]},{"name":"lizard.zip","url":"https://myrient.erista.me/files/MAME/Software%20List%20ROMs%20%28split%29/mz2500_flop/lizard.zip","size":"118.9 KiB","path":["MAME","Software List ROMs (split)","mz2500_flop"]},{"name":"macadam.zip","url":"https://myrient.erista.me/files/MAME/Software%20List%20ROMs%20%28split%29/mz2500_flop/macadam.zip","size":"206.8 KiB","path":["MAME","Software List ROMs (split)","mz2500_flop"]},{"name":"mappy.zip","url":"https://myrient.erista.me/files/MAME/Software%20List%20ROMs%20%28split%29/mz2500_flop/mappy.zip","size":"43.2 KiB","path":["MAME","Software List ROMs (split)","mz2500_flop"]},{"name":"marchen.zip","url":"https://myrient.erista.me/files/MAME/Software%20List%20ROMs%20%28split%29/mz2500_flop/marchen.zip","size":"156.6 KiB","path":["MAME","Software List ROMs (split)","mz2500_flop"]},{"name":"marvels.zip","url":"https://myrient.erista.me/files/MAME/Software%20List%20ROMs%20%28split%29/mz2500_flop/marvels.zip","size":"330.2 KiB","path":["MAME","Software List ROMs (split)","mz2500_flop"]},{"name":"mclown.zip","url":"https://myrient.erista.me/files/MAME/Software%20List%20ROMs%20%28split%29/mz2500_flop/mclown.zip","size":"596.2 KiB","path":["MAME","Software List ROMs (split)","mz2500_flop"]},{"name":"moonchld.zip","url":"https://myrient.erista.me/files/MAME/Software%20List%20ROMs%20%28split%29/mz2500_flop/moonchld.zip","size":"268.7 KiB","path":["MAME","Software List ROMs (split)","mz2500_flop"]},{"name":"mugen.zip","url":"https://myrient.erista.me/files/MAME/Software%20List%20ROMs%20%28split%29/mz2500_flop/mugen.zip","size":"272.0 KiB","path":["MAME","Software List ROMs (split)","mz2500_flop"]},{"name":"mugen2.zip","url":"https://myrient.erista.me/files/MAME/Software%20List%20ROMs%20%28split%29/mz2500_flop/mugen2.zip","size":"306.1 KiB","path":["MAME","Software List ROMs (split)","mz2500_flop"]},{"name":"multplan.zip","url":"https://myrient.erista.me/files/MAME/Software%20List%20ROMs%20%28split%29/mz2500_flop/multplan.zip","size":"181.9 KiB","path":["MAME","Software List ROMs (split)","mz2500_flop"]},{"name":"murdclub.zip","url":"https://myrient.erista.me/files/MAME/Software%20List%20ROMs%20%28split%29/mz2500_flop/murdclub.zip","size":"713.2 KiB","path":["MAME","Software List ROMs (split)","mz2500_flop"]},{"name":"mzdemo1.zip","url":"https://myrient.erista.me/files/MAME/Software%20List%20ROMs%20%28split%29/mz2500_flop/mzdemo1.zip","size":"167.3 KiB","path":["MAME","Software List ROMs (split)","mz2500_flop"]},{"name":"nobo.zip","url":"https://myrient.erista.me/files/MAME/Software%20List%20ROMs%20%28split%29/mz2500_flop/nobo.zip","size":"27.1 KiB","path":["MAME","Software List ROMs (split)","mz2500_flop"]},{"name":"nobunaga.zip","url":"https://myrient.erista.me/files/MAME/Software%20List%20ROMs%20%28split%29/mz2500_flop/nobunaga.zip","size":"198.9 KiB","path":["MAME","Software List ROMs (split)","mz2500_flop"]},{"name":"pcpm.zip","url":"https://myrient.erista.me/files/MAME/Software%20List%20ROMs%20%28split%29/mz2500_flop/pcpm.zip","size":"204.2 KiB","path":["MAME","Software List ROMs (split)","mz2500_flop"]},{"name":"penguinw.zip","url":"https://myrient.erista.me/files/MAME/Software%20List%20ROMs%20%28split%29/mz2500_flop/penguinw.zip","size":"40.0 KiB","path":["MAME","Software List ROMs (split)","mz2500_flop"]},{"name":"profmj.zip","url":"https://myrient.erista.me/files/MAME/Software%20List%20ROMs%20%28split%29/mz2500_flop/profmj.zip","size":"24.9 KiB","path":["MAME","Software List ROMs (split)","mz2500_flop"]},{"name":"profmja.zip","url":"https://myrient.erista.me/files/MAME/Software%20List%20ROMs%20%28split%29/mz2500_flop/profmja.zip","size":"25.1 KiB","path":["MAME","Software List ROMs (split)","mz2500_flop"]},{"name":"rebirth.zip","url":"https://myrient.erista.me/files/MAME/Software%20List%20ROMs%20%28split%29/mz2500_flop/rebirth.zip","size":"947.4 KiB","path":["MAME","Software List ROMs (split)","mz2500_flop"]},{"name":"relics.zip","url":"https://myrient.erista.me/files/MAME/Software%20List%20ROMs%20%28split%29/mz2500_flop/relics.zip","size":"229.2 KiB","path":["MAME","Software List ROMs (split)","mz2500_flop"]},{"name":"sangoku.zip","url":"https://myrient.erista.me/files/MAME/Software%20List%20ROMs%20%28split%29/mz2500_flop/sangoku.zip","size":"347.8 KiB","path":["MAME","Software List ROMs (split)","mz2500_flop"]},{"name":"scobol.zip","url":"https://myrient.erista.me/files/MAME/Software%20List%20ROMs%20%28split%29/mz2500_flop/scobol.zip","size":"36.1 KiB","path":["MAME","Software List ROMs (split)","mz2500_flop"]},{"name":"scpmwm.zip","url":"https://myrient.erista.me/files/MAME/Software%20List%20ROMs%20%28split%29/mz2500_flop/scpmwm.zip","size":"192.1 KiB","path":["MAME","Software List ROMs (split)","mz2500_flop"]},{"name":"simulwar.zip","url":"https://myrient.erista.me/files/MAME/Software%20List%20ROMs%20%28split%29/mz2500_flop/simulwar.zip","size":"360.1 KiB","path":["MAME","Software List ROMs (split)","mz2500_flop"]},{"name":"soundgal.zip","url":"https://myrient.erista.me/files/MAME/Software%20List%20ROMs%20%28split%29/mz2500_flop/soundgal.zip","size":"153.6 KiB","path":["MAME","Software List ROMs (split)","mz2500_flop"]},{"name":"telephon.zip","url":"https://myrient.erista.me/files/MAME/Software%20List%20ROMs%20%28split%29/mz2500_flop/telephon.zip","size":"173.2 KiB","path":["MAME","Software List ROMs (split)","mz2500_flop"]},{"name":"telephona.zip","url":"https://myrient.erista.me/files/MAME/Software%20List%20ROMs%20%28split%29/mz2500_flop/telephona.zip","size":"102.4 KiB","path":["MAME","Software List ROMs (split)","mz2500_flop"]},{"name":"triton.zip","url":"https://myrient.erista.me/files/MAME/Software%20List%20ROMs%20%28split%29/mz2500_flop/triton.zip","size":"89.8 KiB","path":["MAME","Software List ROMs (split)","mz2500_flop"]},{"name":"unk1.zip","url":"https://myrient.erista.me/files/MAME/Software%20List%20ROMs%20%28split%29/mz2500_flop/unk1.zip","size":"201.5 KiB","path":["MAME","Software List ROMs (split)","mz2500_flop"]},{"name":"unk2.zip","url":"https://myrient.erista.me/files/MAME/Software%20List%20ROMs%20%28split%29/mz2500_flop/unk2.zip","size":"21.9 KiB","path":["MAME","Software List ROMs (split)","mz2500_flop"]},{"name":"unk3.zip","url":"https://myrient.erista.me/files/MAME/Software%20List%20ROMs%20%28split%29/mz2500_flop/unk3.zip","size":"229.0 KiB","path":["MAME","Software List ROMs (split)","mz2500_flop"]},{"name":"unk4.zip","url":"https://myrient.erista.me/files/MAME/Software%20List%20ROMs%20%28split%29/mz2500_flop/unk4.zip","size":"155.6 KiB","path":["MAME","Software List ROMs (split)","mz2500_flop"]},{"name":"unk5.zip","url":"https://myrient.erista.me/files/MAME/Software%20List%20ROMs%20%28split%29/mz2500_flop/unk5.zip","size":"68.4 KiB","path":["MAME","Software List ROMs (split)","mz2500_flop"]},{"name":"unk6.zip","url":"https://myrient.erista.me/files/MAME/Software%20List%20ROMs%20%28split%29/mz2500_flop/unk6.zip","size":"16.7 KiB","path":["MAME","Software List ROMs (split)","mz2500_flop"]},{"name":"xevious.zip","url":"https://myrient.erista.me/files/MAME/Software%20List%20ROMs%20%28split%29/mz2500_flop/xevious.zip","size":"205.2 KiB","path":["MAME","Software List ROMs (split)","mz2500_flop"]},{"name":"ys3.zip","url":"https://myrient.erista.me/files/MAME/Software%20List%20ROMs%20%28split%29/mz2500_flop/ys3.zip","size":"732.8 KiB","path":["MAME","Software List ROMs (split)","mz2500_flop"]},{"name":"yukark2.zip","url":"https://myrient.erista.me/files/MAME/Software%20List%20ROMs%20%28split%29/mz2500_flop/yukark2.zip","size":"731.5 KiB","path":["MAME","Software List ROMs (split)","mz2500_flop"]}]