[{"name":"mspepack.zip","url":"https://myrient.erista.me/files/MAME/Software%20List%20ROMs%20%28merged%29/mz800_rom/mspepack.zip","size":"46.2 KiB","path":["MAME","Software List ROMs (merged)","mz800_rom"]},{"name":"rcfaix.zip","url":"https://myrient.erista.me/files/MAME/Software%20List%20ROMs%20%28merged%29/mz800_rom/rcfaix.zip","size":"25.3 KiB","path":["MAME","Software List ROMs (merged)","mz800_rom"]},{"name":"rcsharp.zip","url":"https://myrient.erista.me/files/MAME/Software%20List%20ROMs%20%28merged%29/mz800_rom/rcsharp.zip","size":"44.4 KiB","path":["MAME","Software List ROMs (merged)","mz800_rom"]},{"name":"rcunk.zip","url":"https://myrient.erista.me/files/MAME/Software%20List%20ROMs%20%28merged%29/mz800_rom/rcunk.zip","size":"45.3 KiB","path":["MAME","Software List ROMs (merged)","mz800_rom"]}]