[{"name":"bakumats.zip","url":"https://myrient.erista.me/files/MAME/Software%20List%20ROMs%20%28merged%29/ngpc/bakumats.zip","size":"1008.8 KiB","path":["MAME","Software List ROMs (merged)","ngpc"]},{"name":"bikkuri.zip","url":"https://myrient.erista.me/files/MAME/Software%20List%20ROMs%20%28merged%29/ngpc/bikkuri.zip","size":"724.1 KiB","path":["MAME","Software List ROMs (merged)","ngpc"]},{"name":"biomotor.zip","url":"https://myrient.erista.me/files/MAME/Software%20List%20ROMs%20%28merged%29/ngpc/biomotor.zip","size":"1.2 MiB","path":["MAME","Software List ROMs (merged)","ngpc"]},{"name":"bstarsc.zip","url":"https://myrient.erista.me/files/MAME/Software%20List%20ROMs%20%28merged%29/ngpc/bstarsc.zip","size":"371.0 KiB","path":["MAME","Software List ROMs (merged)","ngpc"]},{"name":"coolboar.zip","url":"https://myrient.erista.me/files/MAME/Software%20List%20ROMs%20%28merged%29/ngpc/coolboar.zip","size":"381.5 KiB","path":["MAME","Software List ROMs (merged)","ngpc"]},{"name":"coolcool.zip","url":"https://myrient.erista.me/files/MAME/Software%20List%20ROMs%20%28merged%29/ngpc/coolcool.zip","size":"916.8 KiB","path":["MAME","Software List ROMs (merged)","ngpc"]},{"name":"cotton.zip","url":"https://myrient.erista.me/files/MAME/Software%20List%20ROMs%20%28merged%29/ngpc/cotton.zip","size":"666.2 KiB","path":["MAME","Software List ROMs (merged)","ngpc"]},{"name":"crushrol.zip","url":"https://myrient.erista.me/files/MAME/Software%20List%20ROMs%20%28merged%29/ngpc/crushrol.zip","size":"491.7 KiB","path":["MAME","Software List ROMs (merged)","ngpc"]},{"name":"darkarms.zip","url":"https://myrient.erista.me/files/MAME/Software%20List%20ROMs%20%28merged%29/ngpc/darkarms.zip","size":"1.2 MiB","path":["MAME","Software List ROMs (merged)","ngpc"]},{"name":"deltawrp.zip","url":"https://myrient.erista.me/files/MAME/Software%20List%20ROMs%20%28merged%29/ngpc/deltawrp.zip","size":"146.5 KiB","path":["MAME","Software List ROMs (merged)","ngpc"]},{"name":"dendego2.zip","url":"https://myrient.erista.me/files/MAME/Software%20List%20ROMs%20%28merged%29/ngpc/dendego2.zip","size":"1.8 MiB","path":["MAME","Software List ROMs (merged)","ngpc"]},{"name":"divealrb.zip","url":"https://myrient.erista.me/files/MAME/Software%20List%20ROMs%20%28merged%29/ngpc/divealrb.zip","size":"1.1 MiB","path":["MAME","Software List ROMs (merged)","ngpc"]},{"name":"divealrm.zip","url":"https://myrient.erista.me/files/MAME/Software%20List%20ROMs%20%28merged%29/ngpc/divealrm.zip","size":"1.5 MiB","path":["MAME","Software List ROMs (merged)","ngpc"]},{"name":"dokodemo.zip","url":"https://myrient.erista.me/files/MAME/Software%20List%20ROMs%20%28merged%29/ngpc/dokodemo.zip","size":"182.3 KiB","path":["MAME","Software List ROMs (merged)","ngpc"]},{"name":"dynaslug.zip","url":"https://myrient.erista.me/files/MAME/Software%20List%20ROMs%20%28merged%29/ngpc/dynaslug.zip","size":"441.7 KiB","path":["MAME","Software List ROMs (merged)","ngpc"]},{"name":"evolutn.zip","url":"https://myrient.erista.me/files/MAME/Software%20List%20ROMs%20%28merged%29/ngpc/evolutn.zip","size":"1.2 MiB","path":["MAME","Software List ROMs (merged)","ngpc"]},{"name":"faselei.zip","url":"https://myrient.erista.me/files/MAME/Software%20List%20ROMs%20%28merged%29/ngpc/faselei.zip","size":"1.9 MiB","path":["MAME","Software List ROMs (merged)","ngpc"]},{"name":"fatfury.zip","url":"https://myrient.erista.me/files/MAME/Software%20List%20ROMs%20%28merged%29/ngpc/fatfury.zip","size":"1.6 MiB","path":["MAME","Software List ROMs (merged)","ngpc"]},{"name":"ganbaren.zip","url":"https://myrient.erista.me/files/MAME/Software%20List%20ROMs%20%28merged%29/ngpc/ganbaren.zip","size":"813.5 KiB","path":["MAME","Software List ROMs (merged)","ngpc"]},{"name":"hanadojo.zip","url":"https://myrient.erista.me/files/MAME/Software%20List%20ROMs%20%28merged%29/ngpc/hanadojo.zip","size":"80.3 KiB","path":["MAME","Software List ROMs (merged)","ngpc"]},{"name":"infinity.zip","url":"https://myrient.erista.me/files/MAME/Software%20List%20ROMs%20%28merged%29/ngpc/infinity.zip","size":"579.7 KiB","path":["MAME","Software List ROMs (merged)","ngpc"]},{"name":"kikousei.zip","url":"https://myrient.erista.me/files/MAME/Software%20List%20ROMs%20%28merged%29/ngpc/kikousei.zip","size":"1.1 MiB","path":["MAME","Software List ROMs (merged)","ngpc"]},{"name":"kofpara.zip","url":"https://myrient.erista.me/files/MAME/Software%20List%20ROMs%20%28merged%29/ngpc/kofpara.zip","size":"740.3 KiB","path":["MAME","Software List ROMs (merged)","ngpc"]},{"name":"kofr2.zip","url":"https://myrient.erista.me/files/MAME/Software%20List%20ROMs%20%28merged%29/ngpc/kofr2.zip","size":"2.5 MiB","path":["MAME","Software List ROMs (merged)","ngpc"]},{"name":"koikoi.zip","url":"https://myrient.erista.me/files/MAME/Software%20List%20ROMs%20%28merged%29/ngpc/koikoi.zip","size":"199.4 KiB","path":["MAME","Software List ROMs (merged)","ngpc"]},{"name":"lastblad.zip","url":"https://myrient.erista.me/files/MAME/Software%20List%20ROMs%20%28merged%29/ngpc/lastblad.zip","size":"1008.1 KiB","path":["MAME","Software List ROMs (merged)","ngpc"]},{"name":"magdrop.zip","url":"https://myrient.erista.me/files/MAME/Software%20List%20ROMs%20%28merged%29/ngpc/magdrop.zip","size":"821.0 KiB","path":["MAME","Software List ROMs (merged)","ngpc"]},{"name":"memories.zip","url":"https://myrient.erista.me/files/MAME/Software%20List%20ROMs%20%28merged%29/ngpc/memories.zip","size":"270.6 KiB","path":["MAME","Software List ROMs (merged)","ngpc"]},{"name":"mezase.zip","url":"https://myrient.erista.me/files/MAME/Software%20List%20ROMs%20%28merged%29/ngpc/mezase.zip","size":"400.3 KiB","path":["MAME","Software List ROMs (merged)","ngpc"]},{"name":"mizuki.zip","url":"https://myrient.erista.me/files/MAME/Software%20List%20ROMs%20%28merged%29/ngpc/mizuki.zip","size":"557.3 KiB","path":["MAME","Software List ROMs (merged)","ngpc"]},{"name":"mslug1st.zip","url":"https://myrient.erista.me/files/MAME/Software%20List%20ROMs%20%28merged%29/ngpc/mslug1st.zip","size":"1.2 MiB","path":["MAME","Software List ROMs (merged)","ngpc"]},{"name":"mslug2nd.zip","url":"https://myrient.erista.me/files/MAME/Software%20List%20ROMs%20%28merged%29/ngpc/mslug2nd.zip","size":"2.1 MiB","path":["MAME","Software List ROMs (merged)","ngpc"]},{"name":"neo21.zip","url":"https://myrient.erista.me/files/MAME/Software%20List%20ROMs%20%28merged%29/ngpc/neo21.zip","size":"202.3 KiB","path":["MAME","Software List ROMs (merged)","ngpc"]},{"name":"neobacca.zip","url":"https://myrient.erista.me/files/MAME/Software%20List%20ROMs%20%28merged%29/ngpc/neobacca.zip","size":"273.3 KiB","path":["MAME","Software List ROMs (merged)","ngpc"]},{"name":"neocherc.zip","url":"https://myrient.erista.me/files/MAME/Software%20List%20ROMs%20%28merged%29/ngpc/neocherc.zip","size":"283.3 KiB","path":["MAME","Software List ROMs (merged)","ngpc"]},{"name":"neocuppl.zip","url":"https://myrient.erista.me/files/MAME/Software%20List%20ROMs%20%28merged%29/ngpc/neocuppl.zip","size":"471.0 KiB","path":["MAME","Software List ROMs (merged)","ngpc"]},{"name":"neoderby.zip","url":"https://myrient.erista.me/files/MAME/Software%20List%20ROMs%20%28merged%29/ngpc/neoderby.zip","size":"499.9 KiB","path":["MAME","Software List ROMs (merged)","ngpc"]},{"name":"neodrag.zip","url":"https://myrient.erista.me/files/MAME/Software%20List%20ROMs%20%28merged%29/ngpc/neodrag.zip","size":"464.7 KiB","path":["MAME","Software List ROMs (merged)","ngpc"]},{"name":"neomystr.zip","url":"https://myrient.erista.me/files/MAME/Software%20List%20ROMs%20%28merged%29/ngpc/neomystr.zip","size":"142.4 KiB","path":["MAME","Software List ROMs (merged)","ngpc"]},{"name":"neoproyk.zip","url":"https://myrient.erista.me/files/MAME/Software%20List%20ROMs%20%28merged%29/ngpc/neoproyk.zip","size":"435.3 KiB","path":["MAME","Software List ROMs (merged)","ngpc"]},{"name":"neoturfm.zip","url":"https://myrient.erista.me/files/MAME/Software%20List%20ROMs%20%28merged%29/ngpc/neoturfm.zip","size":"629.9 KiB","path":["MAME","Software List ROMs (merged)","ngpc"]},{"name":"nigeronp.zip","url":"https://myrient.erista.me/files/MAME/Software%20List%20ROMs%20%28merged%29/ngpc/nigeronp.zip","size":"509.2 KiB","path":["MAME","Software List ROMs (merged)","ngpc"]},{"name":"oekakip.zip","url":"https://myrient.erista.me/files/MAME/Software%20List%20ROMs%20%28merged%29/ngpc/oekakip.zip","size":"113.0 KiB","path":["MAME","Software List ROMs (merged)","ngpc"]},{"name":"ogrebatl.zip","url":"https://myrient.erista.me/files/MAME/Software%20List%20ROMs%20%28merged%29/ngpc/ogrebatl.zip","size":"694.5 KiB","path":["MAME","Software List ROMs (merged)","ngpc"]},{"name":"pachinko.zip","url":"https://myrient.erista.me/files/MAME/Software%20List%20ROMs%20%28merged%29/ngpc/pachinko.zip","size":"617.0 KiB","path":["MAME","Software List ROMs (merged)","ngpc"]},{"name":"pacman.zip","url":"https://myrient.erista.me/files/MAME/Software%20List%20ROMs%20%28merged%29/ngpc/pacman.zip","size":"34.0 KiB","path":["MAME","Software List ROMs (merged)","ngpc"]},{"name":"pbobble.zip","url":"https://myrient.erista.me/files/MAME/Software%20List%20ROMs%20%28merged%29/ngpc/pbobble.zip","size":"1.5 MiB","path":["MAME","Software List ROMs (merged)","ngpc"]},{"name":"picturep.zip","url":"https://myrient.erista.me/files/MAME/Software%20List%20ROMs%20%28merged%29/ngpc/picturep.zip","size":"451.5 KiB","path":["MAME","Software List ROMs (merged)","ngpc"]},{"name":"pockrev.zip","url":"https://myrient.erista.me/files/MAME/Software%20List%20ROMs%20%28merged%29/ngpc/pockrev.zip","size":"472.3 KiB","path":["MAME","Software List ROMs (merged)","ngpc"]},{"name":"pockrevj.zip","url":"https://myrient.erista.me/files/MAME/Software%20List%20ROMs%20%28merged%29/ngpc/pockrevj.zip","size":"121.5 KiB","path":["MAME","Software List ROMs (merged)","ngpc"]},{"name":"poktlove.zip","url":"https://myrient.erista.me/files/MAME/Software%20List%20ROMs%20%28merged%29/ngpc/poktlove.zip","size":"973.8 KiB","path":["MAME","Software List ROMs (merged)","ngpc"]},{"name":"ppaa01.zip","url":"https://myrient.erista.me/files/MAME/Software%20List%20ROMs%20%28merged%29/ngpc/ppaa01.zip","size":"39.5 KiB","path":["MAME","Software List ROMs (merged)","ngpc"]},{"name":"prtymail.zip","url":"https://myrient.erista.me/files/MAME/Software%20List%20ROMs%20%28merged%29/ngpc/prtymail.zip","size":"457.6 KiB","path":["MAME","Software List ROMs (merged)","ngpc"]},{"name":"pslotazt.zip","url":"https://myrient.erista.me/files/MAME/Software%20List%20ROMs%20%28merged%29/ngpc/pslotazt.zip","size":"155.1 KiB","path":["MAME","Software List ROMs (merged)","ngpc"]},{"name":"pslotdk2.zip","url":"https://myrient.erista.me/files/MAME/Software%20List%20ROMs%20%28merged%29/ngpc/pslotdk2.zip","size":"391.0 KiB","path":["MAME","Software List ROMs (merged)","ngpc"]},{"name":"pslotds2.zip","url":"https://myrient.erista.me/files/MAME/Software%20List%20ROMs%20%28merged%29/ngpc/pslotds2.zip","size":"248.2 KiB","path":["MAME","Software List ROMs (merged)","ngpc"]},{"name":"pslotecp.zip","url":"https://myrient.erista.me/files/MAME/Software%20List%20ROMs%20%28merged%29/ngpc/pslotecp.zip","size":"354.6 KiB","path":["MAME","Software List ROMs (merged)","ngpc"]},{"name":"pslothan.zip","url":"https://myrient.erista.me/files/MAME/Software%20List%20ROMs%20%28merged%29/ngpc/pslothan.zip","size":"224.4 KiB","path":["MAME","Software List ROMs (merged)","ngpc"]},{"name":"pslotooh.zip","url":"https://myrient.erista.me/files/MAME/Software%20List%20ROMs%20%28merged%29/ngpc/pslotooh.zip","size":"186.7 KiB","path":["MAME","Software List ROMs (merged)","ngpc"]},{"name":"pslotpc2.zip","url":"https://myrient.erista.me/files/MAME/Software%20List%20ROMs%20%28merged%29/ngpc/pslotpc2.zip","size":"164.1 KiB","path":["MAME","Software List ROMs (merged)","ngpc"]},{"name":"pslotwrd.zip","url":"https://myrient.erista.me/files/MAME/Software%20List%20ROMs%20%28merged%29/ngpc/pslotwrd.zip","size":"143.7 KiB","path":["MAME","Software List ROMs (merged)","ngpc"]},{"name":"ptennisc.zip","url":"https://myrient.erista.me/files/MAME/Software%20List%20ROMs%20%28merged%29/ngpc/ptennisc.zip","size":"204.0 KiB","path":["MAME","Software List ROMs (merged)","ngpc"]},{"name":"puyopop.zip","url":"https://myrient.erista.me/files/MAME/Software%20List%20ROMs%20%28merged%29/ngpc/puyopop.zip","size":"1.1 MiB","path":["MAME","Software List ROMs (merged)","ngpc"]},{"name":"puzzlink.zip","url":"https://myrient.erista.me/files/MAME/Software%20List%20ROMs%20%28merged%29/ngpc/puzzlink.zip","size":"300.1 KiB","path":["MAME","Software List ROMs (merged)","ngpc"]},{"name":"puzzlnk2.zip","url":"https://myrient.erista.me/files/MAME/Software%20List%20ROMs%20%28merged%29/ngpc/puzzlnk2.zip","size":"677.7 KiB","path":["MAME","Software List ROMs (merged)","ngpc"]},{"name":"rockmanb.zip","url":"https://myrient.erista.me/files/MAME/Software%20List%20ROMs%20%28merged%29/ngpc/rockmanb.zip","size":"954.9 KiB","path":["MAME","Software List ROMs (merged)","ngpc"]},{"name":"rockmanbd.zip","url":"https://myrient.erista.me/files/MAME/Software%20List%20ROMs%20%28merged%29/ngpc/rockmanbd.zip","size":"963.4 KiB","path":["MAME","Software List ROMs (merged)","ngpc"]},{"name":"samsho2.zip","url":"https://myrient.erista.me/files/MAME/Software%20List%20ROMs%20%28merged%29/ngpc/samsho2.zip","size":"932.3 KiB","path":["MAME","Software List ROMs (merged)","ngpc"]},{"name":"shanghai.zip","url":"https://myrient.erista.me/files/MAME/Software%20List%20ROMs%20%28merged%29/ngpc/shanghai.zip","size":"727.4 KiB","path":["MAME","Software List ROMs (merged)","ngpc"]},{"name":"shougic.zip","url":"https://myrient.erista.me/files/MAME/Software%20List%20ROMs%20%28merged%29/ngpc/shougic.zip","size":"154.4 KiB","path":["MAME","Software List ROMs (merged)","ngpc"]},{"name":"snkgals.zip","url":"https://myrient.erista.me/files/MAME/Software%20List%20ROMs%20%28merged%29/ngpc/snkgals.zip","size":"1.7 MiB","path":["MAME","Software List ROMs (merged)","ngpc"]},{"name":"sonic.zip","url":"https://myrient.erista.me/files/MAME/Software%20List%20ROMs%20%28merged%29/ngpc/sonic.zip","size":"1.9 MiB","path":["MAME","Software List ROMs (merged)","ngpc"]},{"name":"srmp.zip","url":"https://myrient.erista.me/files/MAME/Software%20List%20ROMs%20%28merged%29/ngpc/srmp.zip","size":"874.8 KiB","path":["MAME","Software List ROMs (merged)","ngpc"]},{"name":"svc.zip","url":"https://myrient.erista.me/files/MAME/Software%20List%20ROMs%20%28merged%29/ngpc/svc.zip","size":"2.5 MiB","path":["MAME","Software List ROMs (merged)","ngpc"]},{"name":"svccard2.zip","url":"https://myrient.erista.me/files/MAME/Software%20List%20ROMs%20%28merged%29/ngpc/svccard2.zip","size":"976.0 KiB","path":["MAME","Software List ROMs (merged)","ngpc"]},{"name":"svccardc.zip","url":"https://myrient.erista.me/files/MAME/Software%20List%20ROMs%20%28merged%29/ngpc/svccardc.zip","size":"1.7 MiB","path":["MAME","Software List ROMs (merged)","ngpc"]},{"name":"svccards.zip","url":"https://myrient.erista.me/files/MAME/Software%20List%20ROMs%20%28merged%29/ngpc/svccards.zip","size":"3.4 MiB","path":["MAME","Software List ROMs (merged)","ngpc"]},{"name":"wrestmad.zip","url":"https://myrient.erista.me/files/MAME/Software%20List%20ROMs%20%28merged%29/ngpc/wrestmad.zip","size":"1.9 MiB","path":["MAME","Software List ROMs (merged)","ngpc"]}]