[{"name":"sbsp1.zip","url":"https://myrient.erista.me/files/MAME/Software%20List%20ROMs%20%28split%29/digiblast_cart/sbsp1.zip","size":"61.6 MiB","path":["MAME","Software List ROMs (split)","digiblast_cart"]},{"name":"sonicx1.zip","url":"https://myrient.erista.me/files/MAME/Software%20List%20ROMs%20%28split%29/digiblast_cart/sonicx1.zip","size":"55.7 MiB","path":["MAME","Software List ROMs (split)","digiblast_cart"]},{"name":"totsp1.zip","url":"https://myrient.erista.me/files/MAME/Software%20List%20ROMs%20%28split%29/digiblast_cart/totsp1.zip","size":"52.7 MiB","path":["MAME","Software List ROMs (split)","digiblast_cart"]},{"name":"winx1.zip","url":"https://myrient.erista.me/files/MAME/Software%20List%20ROMs%20%28split%29/digiblast_cart/winx1.zip","size":"61.7 MiB","path":["MAME","Software List ROMs (split)","digiblast_cart"]},{"name":"wxatari.zip","url":"https://myrient.erista.me/files/MAME/Software%20List%20ROMs%20%28split%29/digiblast_cart/wxatari.zip","size":"52.3 MiB","path":["MAME","Software List ROMs (split)","digiblast_cart"]},{"name":"yugi.zip","url":"https://myrient.erista.me/files/MAME/Software%20List%20ROMs%20%28split%29/digiblast_cart/yugi.zip","size":"59.5 MiB","path":["MAME","Software List ROMs (split)","digiblast_cart"]}]